share/locale/.gitignore
share/locale/de/LC_MESSAGES/derivepassphrase.mo
share/locale/en_US@DEBUG/LC_MESSAGES/derivepassphrase.mo
share/man/man1/derivepassphrase-export-vault.1
share/man/man1/derivepassphrase-export.1
share/man/man1/derivepassphrase-vault.1
share/man/man1/derivepassphrase.1
derivepassphrase/__init__.py
derivepassphrase/__main__.py
derivepassphrase/_types.py
derivepassphrase/cli.py
derivepassphrase/py.typed
derivepassphrase/sequin.py
derivepassphrase/ssh_agent.py
derivepassphrase/vault.py
derivepassphrase/_internals/__init__.py
derivepassphrase/_internals/cli_helpers.py
derivepassphrase/_internals/cli_machinery.py
derivepassphrase/_internals/cli_messages.py
derivepassphrase/exporter/__init__.py
derivepassphrase/exporter/storeroom.py
derivepassphrase/exporter/vault_native.py
derivepassphrase-0.5.2.dist-info/METADATA
derivepassphrase-0.5.2.dist-info/WHEEL
derivepassphrase-0.5.2.dist-info/entry_points.txt
derivepassphrase-0.5.2.dist-info/licenses/LICENSE.txt
derivepassphrase-0.5.2.dist-info/RECORD
