Metadata-Version: 2.4
Name: derivepassphrase
Version: 0.5.2
Summary: An almost faithful Python reimplementation of James Coglan's vault.
Project-URL: Documentation, https://the13thletter.info/derivepassphrase/
Project-URL: Issues, https://the13thletter.info/derivepassphrase/latest/wishlist/
Project-URL: Source, https://git.schokokeks.org/derivepassphrase.git
Author-email: Marco Ricci <software@the13thletter.info>
License: zlib/libpng
License-File: LICENSE.txt
Classifier: Development Status :: 4 - Beta
Classifier: Environment :: Console
Classifier: License :: OSI Approved :: zlib/libpng License
Classifier: Programming Language :: Python :: 3
Classifier: Programming Language :: Python :: 3.9
Classifier: Programming Language :: Python :: 3.10
Classifier: Programming Language :: Python :: 3.11
Classifier: Programming Language :: Python :: 3.12
Classifier: Programming Language :: Python :: 3.13
Classifier: Programming Language :: Python :: 3.14
Classifier: Programming Language :: Python :: Implementation :: CPython
Classifier: Programming Language :: Python :: Implementation :: PyPy
Requires-Python: >=3.9
Requires-Dist: click>=8.1
Requires-Dist: tomli; python_version < '3.11'
Requires-Dist: typing-extensions
Provides-Extra: dev
Requires-Dist: coverage-enable-subprocess>=1.0; extra == 'dev'
Requires-Dist: coverage[toml]>=7.4; extra == 'dev'
Requires-Dist: hatch>=1.10; extra == 'dev'
Requires-Dist: hypothesis!=6.130.13,!=6.131.*,!=6.132.*,!=6.133.*,!=6.134.*,!=6.135.0,!=6.135.1; (python_version < '3.10') and extra == 'dev'
Requires-Dist: hypothesis>=6.0; extra == 'dev'
Requires-Dist: mypy>=1.0; extra == 'dev'
Requires-Dist: packaging; extra == 'dev'
Requires-Dist: pytest-randomly>=3.15; extra == 'dev'
Requires-Dist: pytest-xdist>=3.6.0; extra == 'dev'
Requires-Dist: pytest-xdist[psutil]>=3.6.0; (platform_python_implementation != 'PyPy') and extra == 'dev'
Requires-Dist: pytest>=8.1; extra == 'dev'
Requires-Dist: ruff>=0.9.0; extra == 'dev'
Provides-Extra: export
Requires-Dist: cryptography>=42.0.0; extra == 'export'
Provides-Extra: export-dev-wheels
Requires-Dist: cryptography<44; (python_version < '3.10' and platform_python_implementation == 'PyPy') and extra == 'export-dev-wheels'
Requires-Dist: cryptography>44.0.1; (python_version >= '3.11' and platform_python_implementation == 'PyPy') and extra == 'export-dev-wheels'
